itspylearning
