Metadata-Version: 2.1
Name: itspylearning
Version: 0.2.4
Summary: An itslearning api python library.
Home-page: https://github.com/HubertJan/itspylearning
Author: Hubert Jan Tomaszczak
License: MIT
Download-URL: https://github.com/HubertJan/itspylearning/archive/refs/tags/v0.2.4.tar.gz
Platform: UNKNOWN
Requires-Python: >=3.10.0,
License-File: LICENCE.txt
